COPYING
MANIFEST.in
NEWS
README
TODO
setup.cfg
setup.py
Dyko.egg-info/PKG-INFO
Dyko.egg-info/SOURCES.txt
Dyko.egg-info/dependency_links.txt
Dyko.egg-info/requires.txt
Dyko.egg-info/top_level.txt
kalamar/__init__.py
kalamar/item.py
kalamar/property.py
kalamar/query.py
kalamar/request.py
kalamar/site.py
kalamar/value.py
kalamar/access_point/__init__.py
kalamar/access_point/aliases.py
kalamar/access_point/cache.py
kalamar/access_point/decorator.py
kalamar/access_point/filesystem.py
kalamar/access_point/memory.py
kalamar/access_point/unicode_stream.py
kalamar/access_point/alchemy/__init__.py
kalamar/access_point/alchemy/querypatch.py
kalamar/access_point/xml/__init__.py
kalamar/access_point/xml/rest.py
kalamar/tests/__init__.py
kalamar/tests/common.py
kalamar/tests/test_common.py
kalamar/tests/test_heterogenous_view.py
kalamar/tests/test_item.py
kalamar/tests/test_normalize.py
kalamar/tests/test_property.py
kalamar/tests/test_request.py
kalamar/tests/test_site.py
kalamar/tests/test_view.py
kalamar/tests/test_view_request.py
kalamar/tests/access_point/__init__.py
kalamar/tests/access_point/test_access_point.py
kalamar/tests/access_point/test_alchemy.py
kalamar/tests/access_point/test_alchemy_multiple_identity.py
kalamar/tests/access_point/test_alchemy_view.py
kalamar/tests/access_point/test_aliases.py
kalamar/tests/access_point/test_cache.py
kalamar/tests/access_point/test_decorator.py
kalamar/tests/access_point/test_filesystem.py
kalamar/tests/access_point/test_memory.py
kalamar/tests/access_point/test_rest.py
kalamar/tests/access_point/test_xml.py
kalamar/tests/combinations/__init__.py
kalamar/tests/combinations/common_tests.py
kalamar/tests/combinations/test_combinations.py
kalamar/tests/combinations/access_point/__init__.py
kalamar/tests/combinations/access_point/alchemy_aps.py
kalamar/tests/combinations/access_point/cache_aps.py
kalamar/tests/combinations/access_point/filesystem_aps.py
kalamar/tests/combinations/access_point/memory_aps.py
kalamar/tests/combinations/access_point/rest_aps.py
kalamar/tests/combinations/access_point/xml_aps.py
kraken/__init__.py
kraken/site.py
kraken/template/__init__.py
