Metadata-Version: 1.1
Name: Dyko
Version: 0.2
Summary: A Lightweight Web Framework
Home-page: http://www.dyko.org/
Author: Kozea
Author-email: guillaume.ayoub@kozea.fr
License: GNU GPL v3
Download-URL: http://www.dyko.org/src/dyko/Dyko-0.2.tar.gz
Keywords: web,framework,database
Platform: Any
Classifier: Development Status :: 3 - Alpha
Classifier: Environment :: Console
Classifier: Environment :: Web Environment
Classifier: Intended Audience :: Information Technology
Classifier: License :: OSI Approved :: GNU General Public License (GPL)
Classifier: Operating System :: OS Independent
Classifier: Programming Language :: Python :: 2
Classifier: Programming Language :: Python :: 2.6
Classifier: Programming Language :: Python :: 2.7
Classifier: Topic :: Software Development :: Libraries :: Application Frameworks
Provides: kalamar
Provides: kraken
